hopeit_agents/mcp_server/cli/__init__.py
hopeit_agents/mcp_server/cli/py.typed
hopeit_agents/mcp_server/cli/server.py
hopeit_agents/mcp_server/server/__init__.py
hopeit_agents/mcp_server/server/handler.py
hopeit_agents/mcp_server/server/mcp.py
hopeit_agents/mcp_server/server/py.typed
hopeit_agents/mcp_server/tools/__init__.py
hopeit_agents/mcp_server/tools/api.py
hopeit_agents/mcp_server/tools/py.typed
hopeit_agents_mcp_server-0.1.0b2.dist-info/METADATA
hopeit_agents_mcp_server-0.1.0b2.dist-info/WHEEL
hopeit_agents_mcp_server-0.1.0b2.dist-info/entry_points.txt
hopeit_agents_mcp_server-0.1.0b2.dist-info/top_level.txt
hopeit_agents_mcp_server-0.1.0b2.dist-info/RECORD
